streamflow/__init__.py
streamflow/__main__.py
streamflow/log_handler.py
streamflow/main.py
streamflow/parser.py
streamflow/report.py
streamflow/version.py
streamflow/config/__init__.py
streamflow/config/config.py
streamflow/config/validator.py
streamflow/config/schemas/v1.0/config_schema.json
streamflow/config/schemas/v1.0/docker-compose.json
streamflow/config/schemas/v1.0/docker.json
streamflow/config/schemas/v1.0/helm2.json
streamflow/config/schemas/v1.0/helm3.json
streamflow/config/schemas/v1.0/occam.json
streamflow/config/schemas/v1.0/queue_manager.json
streamflow/config/schemas/v1.0/singularity.json
streamflow/config/schemas/v1.0/ssh.json
streamflow/core/__init__.py
streamflow/core/asyncache.py
streamflow/core/context.py
streamflow/core/data.py
streamflow/core/deployment.py
streamflow/core/exception.py
streamflow/core/persistence.py
streamflow/core/recovery.py
streamflow/core/scheduling.py
streamflow/core/utils.py
streamflow/core/workflow.py
streamflow/cwl/__init__.py
streamflow/cwl/command.py
streamflow/cwl/condition.py
streamflow/cwl/expression.py
streamflow/cwl/hardware.py
streamflow/cwl/main.py
streamflow/cwl/runner.py
streamflow/cwl/token_processor.py
streamflow/cwl/translator.py
streamflow/cwl/utils.py
streamflow/cwl/antlr/ECMAScriptLexer.py
streamflow/cwl/antlr/ECMAScriptListener.py
streamflow/cwl/antlr/ECMAScriptParser.py
streamflow/cwl/antlr/__init__.py
streamflow/data/__init__.py
streamflow/data/data_manager.py
streamflow/data/remotepath.py
streamflow/deployment/__init__.py
streamflow/deployment/deployment_manager.py
streamflow/deployment/connector/__init__.py
streamflow/deployment/connector/base.py
streamflow/deployment/connector/container.py
streamflow/deployment/connector/kubernetes.py
streamflow/deployment/connector/local.py
streamflow/deployment/connector/occam.py
streamflow/deployment/connector/queue_manager.py
streamflow/deployment/connector/ssh.py
streamflow/persistence/__init__.py
streamflow/persistence/persistence_manager.py
streamflow-0.1.6.dist-info/LICENSE
streamflow-0.1.6.dist-info/METADATA
streamflow-0.1.6.dist-info/WHEEL
streamflow-0.1.6.dist-info/entry_points.txt
streamflow-0.1.6.dist-info/top_level.txt
streamflow-0.1.6.dist-info/zip-safe
streamflow-0.1.6.dist-info/RECORD
