Metadata-Version: 2.1
Name: streamflow
Version: 0.1.6
Summary: StreamFlow framework
Home-page: https://github.com/alpha-unito/streamflow
Download-URL: https://github.com/alpha-unito/streamflow/releases
Author: Iacopo Colonnelli
Author-email: iacopo.colonnelli@unito.it
Classifier: Development Status :: 4 - Beta
Classifier: License :: OSI Approved :: GNU Lesser General Public License v3 (LGPLv3)
Classifier: Intended Audience :: Developers
Classifier: Intended Audience :: Science/Research
Classifier: Operating System :: POSIX
Classifier: Operating System :: MacOS
Classifier: Programming Language :: Python :: 3.8
Classifier: Topic :: Scientific/Engineering
Classifier: Topic :: System :: Distributed Computing
Requires-Python: >=3.8, <4
License-File: LICENSE
Requires-Dist: aiohttp
Requires-Dist: antlr4-python3-runtime (<4.10)
Requires-Dist: asyncssh
Requires-Dist: bcrypt
Requires-Dist: cachetools
Requires-Dist: cwltool
Requires-Dist: Jinja2
Requires-Dist: jsonref
Requires-Dist: jsonschema
Requires-Dist: kubernetes-asyncio (>=22.6.2)
Requires-Dist: pandas
Provides-Extra: docs
Requires-Dist: sphinx ; extra == 'docs'
Requires-Dist: sphinx-jsonschema ; extra == 'docs'
Requires-Dist: sphinx-rtd-theme ; extra == 'docs'
Provides-Extra: report
Requires-Dist: plotly ; extra == 'report'
Requires-Dist: kaleido ; extra == 'report'
